pyab3p.cpython-312-i386-linux-musl.so
pyab3p-0.1.1.dist-info/RECORD
pyab3p-0.1.1.dist-info/WHEEL
pyab3p-0.1.1.dist-info/top_level.txt
pyab3p-0.1.1.dist-info/METADATA
word_data/hshset_Lf1chSf.ha
word_data/cshset_wrdset3.ad
word_data/Ab3P_prec.dat
word_data/hshset_Lf1chSf.nm
word_data/cshset_wrdset3.nm
word_data/Lf1chSf
word_data/hshset_Lf1chSf.str
word_data/hshset_stop.str
word_data/stop
word_data/__init__.py
word_data/cshset_wrdset3.ct
word_data/hshset_Lf1chSf.ad
word_data/hshset_stop.nm
word_data/SingTermFreq.dat
word_data/hshset_stop.ha
word_data/cshset_wrdset3.ha
word_data/hshset_stop.ad
word_data/cshset_wrdset3.str
pyab3p.libs/libgcc_s-8b50eaaa.so.1
pyab3p.libs/libstdc++-8baf04f9.so.6.0.28
