Metadata-Version: 2.1
Name: pyab3p
Version: 0.1.1
Summary: Python bindings for Ab3p
Home-page: https://github.com/helpmefindaname/pyab3p
Author: Benedikt Fuchs
Author-email: benedikt.fuchs.staw@hotmail.com
Requires-Python: >=3.8.0
